ColabGeek/ColabGeek.py
ColabGeek/__init__.py
ColabGeek/shell_scripts/Install_Homebrew.exp
ColabGeek/shell_scripts/Install_Jekyll.exp
ColabGeek/shell_scripts/Install_Miniconda.sh
ColabGeek/shell_scripts/Install_Ruby.exp
ColabGeek/shell_scripts/Install_rbenv.exp
ColabGeek/shell_scripts/Run_Rstudio_server.sh
ColabGeek/shell_scripts/Run_Stable_Diffusion_WebUI.exp
ColabGeek/shell_scripts/Run_code_server.exp
ColabGeek-1.4.1.dist-info/LICENSE
ColabGeek-1.4.1.dist-info/METADATA
ColabGeek-1.4.1.dist-info/WHEEL
ColabGeek-1.4.1.dist-info/top_level.txt
ColabGeek-1.4.1.dist-info/RECORD
