Metadata-Version: 2.1
Name: ColabGeek
Version: 1.4.1
Summary: ColabGeek is designed to help run useful tools on Google Colab, including web IDE, port forwarding and so on.
Author-email: Yiming Sun <yiming.sun12138@gmail.com>
Project-URL: Homepage, https://github.com/yimingsun12138/ColabGeek
Project-URL: Bug Tracker, https://github.com/yimingsun12138/ColabGeek/issues
Classifier: Programming Language :: Python :: 3
Classifier: License :: OSI Approved :: MIT License
Classifier: Operating System :: POSIX :: Linux
Requires-Python: >=3.7
License-File: LICENSE
Provides-Extra: full
Requires-Dist: jupyter-server ; extra == 'full'
